{
    "0": {
        "name": "Player Character Count",
        "description": "Number of characters on account",
        "type": "number",
        "AI": true
    },
    "1": {
        "name": "Chest System",
        "description": "Controls chest functionality and storage operations",
        "type": "number",
        "AI": true
    },
    "2": {
        "name": "UI Scaling Factor",
        "description": "Interface scaling setting for display size",
        "type": "number",
        "AI": true
    },
    "3": {
        "name": "Quick Tap Feature Toggle",
        "description": "Enable/disable quick tap feature (1=On)",
        "type": "number",
        "AI": true
    },
    "4": {
        "name": "Quick Tap Secondary State",
        "description": "Secondary state tracking for quick tap",
        "type": "number",
        "AI": true
    },
    "5": {
        "name": "Skill Point Allocation Amount",
        "description": "Cycling amount (1, 5, 10, 25, 900) for skill points",
        "type": "number",
        "AI": true
    },
    "6": {
        "name": "Enhanced Skill Allocation Mode",
        "description": "Toggle for enhanced skill point allocation interface",
        "type": "number",
        "AI": true
    },
    "7": {
        "name": "AFK Detection/Party Counter",
        "description": "Tracks AFK detection or party member count",
        "type": "number",
        "AI": true
    },
    "8": {
        "name": "Chat Window X Position",
        "description": "Horizontal position of chat window",
        "type": "number",
        "AI": true
    },
    "9": {
        "name": "Chat Window Y Position",
        "description": "Vertical position of chat window",
        "type": "number",
        "AI": true
    },
    "10": {
        "name": "Chat Window Width/Columns",
        "description": "Controls chat window width/column count",
        "type": "number",
        "AI": true
    },
    "11": {
        "name": "Chat Window Height/Rows",
        "description": "Controls chat window height/row count",
        "type": "number",
        "AI": true
    },
    "12": {
        "name": "Chat Window Active State",
        "description": "Chat window visibility state (-1=Inactive, 1=Active)",
        "type": "number"
    },
    "13": {
        "name": "Auto-Transfer/Banking",
        "description": "Toggle for automated banking/transfer features",
        "type": "number",
        "AI": true
    },
    "14": {
        "name": "Achievement/Quest System",
        "description": "Tracks completion of special achievements/trophies",
        "type": "number",
        "AI": true
    },
    "15": {
        "name": "Unclaimed W1 Colosseum Ticket Days",
        "description": "Number of unclaimed W1 colosseum ticket days",
        "type": "number"
    },
    "16": {
        "name": "Unclaimed W1 Boss Keys Days",
        "description": "Number of unclaimed W1 boss keys days",
        "type": "number"
    },
    "17": {
        "name": "Settings Toggle",
        "description": "General settings binary toggle",
        "type": "number",
        "AI": true
    },
    "18": {
        "name": "Chest UI Management",
        "description": "Controls chest interface style and active element",
        "type": "number",
        "AI": true
    },
    "19": {
        "name": "Task Completion Tracking",
        "description": "Tracks completed tasks/skills string",
        "type": "string",
        "AI": true
    },
    "20": {
        "name": "Rating/Popup System",
        "description": "Manages rating prompts display state",
        "type": "number",
        "AI": true
    },
    "21": {
        "name": "Advanced Settings Toggle",
        "description": "Controls advanced settings menu state",
        "type": "number",
        "AI": true
    },
    "22": {
        "name": "Chat Server Message Tracking",
        "description": "Tracks chat-related server message states",
        "type": "number",
        "AI": true
    },
    "23": {
        "name": "Forge/Inventory Auto-Move Toggle",
        "description": "Toggle for auto-move feature in forge/inventory (0/1)",
        "type": "number",
        "AI": true
    },
    "24": {
        "name": "Player/Character Actor Type ID",
        "description": "Player/character actor type identifier and coordinate offset constant",
        "type": "number",
        "AI": true
    },
    "25": {
        "name": "Seasonal Event Item Counter opened",
        "description": "Tracks collected event items opened (coolers, presents, baskets)",
        "type": "number"
    },
    "26": {
        "name": "Shadowban",
        "description": "Set to 0 to remove shadowban",
        "type": "number",
        "warning": "Modifying this may affect your account status"
    },
    "27": {
        "name": "Idleon Discord Button Clicked",
        "description": "Idleon discord button clicked (50 gems)",
        "type": "number"
    },
    "28": {
        "name": "Lava's Twitch Button Clicked",
        "description": "Lava's twitch button clicked (50 gems)",
        "type": "number"
    },
    "29": {
        "name": "Daily Seasonal Event Item Counter dropped",
        "description": "Daily Seasonal Event Item Counter dropped / Event progression counter for free spins",
        "type": "number"
    },
    "30": {
        "name": "BoltCutter Quest Progress",
        "description": "Flag for BoltCutter secret unlock on Map 9",
        "type": "number",
        "AI": true
    },
    "31": {
        "name": "Unclaimed W2 Boss Keys Days",
        "description": "Number of unclaimed W2 boss keys days",
        "type": "number"
    },
    "32": {
        "name": "Cauldron Boost Status",
        "description": "String flags (e.g., '0000') for 4 cauldrons (1=boost active)",
        "type": "string",
        "AI": true
    },
    "33": {
        "name": "Minigames Amount",
        "description": "Number of minigames",
        "type": "number"
    },
    "34": {
        "name": "Inventory Operation Mode",
        "description": "Current inventory interaction mode",
        "type": "number",
        "AI": true
    },
    "35": {
        "name": "Unclaimed W2 Colosseum Ticket Days",
        "description": "Number of unclaimed W2 colosseum ticket days",
        "type": "number"
    },
    "36": {
        "name": "Player Nametag Display Toggle",
        "description": "Controls display of player nametags (0=Enabled)",
        "type": "number",
        "AI": true
    },
    "37": {
        "name": "Guild Name",
        "description": "Your guild name",
        "type": "string"
    },
    "38": {
        "name": "Guild Icon Index",
        "description": "Index of the selected guild icon",
        "type": "number",
        "AI": true
    },
    "39": {
        "name": "Weekly Reset Counter",
        "description": "Tracks weekly reset cycles for shops/divinity",
        "type": "number",
        "AI": true
    },
    "40": {
        "name": "Star Sign Progress",
        "description": "Tracks progress in star sign constellation system",
        "type": "number",
        "AI": true
    },
    "41": {
        "name": "Quest38 Item Counter",
        "description": "Counts special items related to Quest38",
        "type": "number",
        "AI": true
    },
    "42": {
        "name": "Multiplayer Account Flag",
        "description": "Flags accounts with multiple characters",
        "type": "number",
        "AI": true
    },
    "43": {
        "name": "Asset Management System",
        "description": "Asset loading, compression algorithm constants, and actor type identifier",
        "type": "number",
        "AI": true
    },
    "44": {
        "name": "Bundle Expiration Timer",
        "description": "Tracks days remaining for bundle offers",
        "type": "number",
        "AI": true
    },
    "45": {
        "name": "Bundle Cooldown Timer",
        "description": "Tracks bundle activation status and cooldown",
        "type": "number",
        "AI": true
    },
    "46": {
        "name": "Bundle Activation Flag",
        "description": "Indicates if a bundle offer is currently active",
        "type": "number",
        "AI": true
    },
    "47": {
        "name": "Critter Spawning Counter",
        "description": "Tracks NONdummies array for Quest69/critters",
        "type": "number",
        "AI": true
    },
    "48": {
        "name": "Account List Display Mode",
        "description": "Controls player list display style",
        "type": "number",
        "AI": true
    },
    "49": {
        "name": "Starter Bundle Reset",
        "description": "Tracks starter bundle reset timing",
        "type": "number",
        "AI": true
    },
    "50": {
        "name": "Master Volume Control",
        "description": "Overall game audio volume (0-100)",
        "type": "number",
        "AI": true
    },
    "51": {
        "name": "Music Volume Control",
        "description": "Background music volume (0-100)",
        "type": "number",
        "AI": true
    },
    "52": {
        "name": "Effects Volume Control",
        "description": "Sound effects volume (0-100)",
        "type": "number",
        "AI": true
    },
    "53": {
        "name": "Electron App Version",
        "description": "Tracks Desktop/Electron app version state",
        "type": "number",
        "AI": true
    },
    "54": {
        "name": "Asset Positioning System",
        "description": "Asset loading, sprite management, and coordinate positioning",
        "type": "number",
        "AI": true
    },
    "55": {
        "name": "Accumulated Talent Skill Book Checkouts",
        "description": "Total talent skill book checkouts",
        "type": "number"
    },
    "56": {
        "name": "Unclaimed W3 Colosseum Ticket Days",
        "description": "Number of unclaimed W3 colosseum ticket days",
        "type": "number"
    },
    "57": {
        "name": "Giant Mobs Spawn Decrease Multiplier",
        "description": "Controls giant mob spawn rate",
        "type": "number"
    },
    "58": {
        "name": "Quest Categorization & Star Sign Progression",
        "description": "Quest categorization with '^' prefix display marker + StarSignProg tracking array (index 0)",
        "type": "number"
    },
    "59": {
        "name": "Graphics Vertex Buffer & Food System",
        "description": "59th vertex buffer coordinate for rendering + quest item quantities in _ScrollCircleINFO[59] + food slot purchases (2 + GemItemsPurchased[59])",
        "type": "number"
    },
    "60": {
        "name": "Item Shop Popup",
        "description": "Item shop popup setting",
        "type": "number"
    },
    "61": {
        "name": "Localized Text & World Selection",
        "description": "Localized text storage in RANDOlist[61] + world selection system with pagination math ((worldIndex - 1) / 20)",
        "type": "number"
    },
    "62": {
        "name": "Low Capacity Threshold & Hole Parser",
        "description": "Low capacity threshold (80) + primary hole info parser + cooking/anvil/guild state management + quest tracking",
        "type": "number"
    },
    "63": {
        "name": "Medium Capacity Threshold & UI Control",
        "description": "Medium capacity threshold (160) + hole info parsing + monster scaling exponent + UI scrolling control",
        "type": "number"
    },
    "64": {
        "name": "Quest Completion & Monster Scaling",
        "description": "Quest completion flag + high capacity threshold (320) + equipment validation + monster scaling multiplier",
        "type": "number"
    },
    "65": {
        "name": "Frame Rate Configuration",
        "description": "Game frame rate configuration and actor management",
        "type": "number"
    },
    "66": {
        "name": "UI Container & Spirit Reindeer Tracker",
        "description": "UI object container + option cache system + exponential decay timing threshold + Spirit Reindeer location tracking",
        "type": "number"
    },
    "67": {
        "name": "Option Cache & Spelunk Data",
        "description": "Option tracking cache + counter with threshold checking + Spelunk data storage system",
        "type": "number"
    },
    "68": {
        "name": "DO NOT TOUCH",
        "description": "Triggers Abuse Message (different shadowban)",
        "type": "number",
        "warning": "DO NOT MODIFY - Will trigger shadowban"
    },
    "69": {
        "name": "Camera Positioning Actor",
        "description": "Special camera and positioning actor type identifier",
        "type": "number",
        "AI": true
    },
    "70": {
        "name": "Recipe Points",
        "description": "Recipe points tracking",
        "type": "number",
        "AI": true
    },
    "71": {
        "name": "Dungeon Credits (Blue) - Total",
        "description": "Total number - determines rank - keep lower than 100m",
        "type": "number",
        "warning": "Keep lower than 100m"
    },
    "72": {
        "name": "Dungeon Credits (Blue) - Actual",
        "description": "Actual amount of blue dungeon credits",
        "type": "number"
    },
    "73": {
        "name": "Dungeon Credits (Pink/Flurbos)",
        "description": "Pink dungeon credits (flurbos)",
        "type": "number"
    },
    "74": {
        "name": "Arcade Balls (Normal)",
        "description": "Normal arcade balls",
        "type": "number"
    },
    "75": {
        "name": "Arcade Balls (Golden)",
        "description": "Golden arcade balls",
        "type": "number"
    },
    "76": {
        "name": "Character Code L",
        "description": "Character encoding for keyboard input (L=76)",
        "type": "number",
        "AI": true
    },
    "77": {
        "name": "Character Code M",
        "description": "Character encoding for keyboard input (M=77)",
        "type": "number",
        "AI": true
    },
    "78": {
        "name": "Character Code N",
        "description": "Character encoding for keyboard input (N=78)",
        "type": "number",
        "AI": true
    },
    "79": {
        "name": "Character Code O",
        "description": "Character encoding for keyboard input (O=79)",
        "type": "number",
        "AI": true
    },
    "80": {
        "name": "Unclaimed W3 Boss Keys Days",
        "description": "Number of unclaimed W3 boss keys days",
        "type": "number"
    },
    "81": {
        "name": "Tome/Guild State",
        "description": "Tome UI state and Guild join functionality",
        "type": "number",
        "AI": true
    },
    "82": {
        "name": "DoOnceREAL Init",
        "description": "System initialization flag (approx -6.3)",
        "type": "number",
        "AI": true
    },
    "83": {
        "name": "Autoloot toggle",
        "description": "Autoloot toggle (0 = on / 1 = off)",
        "type": "number"
    },
    "84": {
        "name": "Character Code T",
        "description": "Character encoding for keyboard input (T=84)",
        "type": "number",
        "AI": true
    },
    "85": {
        "name": "Quest/Progress Limiter",
        "description": "Quest integration and DoOnce capping logic",
        "type": "number",
        "AI": true
    },
    "86": {
        "name": "Recipe Points",
        "description": "Recipe points (needs confirmation)",
        "type": "number"
    },
    "87": {
        "name": "W4 Breeding Egg Incubation Timer",
        "description": "Elapsed egg incubation time in seconds; increases by 1 every second",
        "type": "number"
    },
    "88": {
        "name": "W4 Arena Timer",
        "description": "World 4 arena timer",
        "type": "number"
    },
    "89": {
        "name": "Character Code Y",
        "description": "Character encoding for keyboard input (Y=89)",
        "type": "number",
        "AI": true
    },
    "90": {
        "name": "Cooking Timer",
        "description": "Tracks cooking activity time",
        "type": "number",
        "AI": true
    },
    "91": {
        "name": "Chip Jewel System",
        "description": "Special item crafting/spawn system",
        "type": "number",
        "AI": true
    },
    "92": {
        "name": "4-Star Cardifiers",
        "description": "Number of 4-star cardifiers",
        "type": "number"
    },
    "93": {
        "name": "Scene Event Identifier",
        "description": "Scene event identification and positioning coordinates",
        "type": "number",
        "AI": true
    },
    "94": {
        "name": "Gem Bundle Tracker",
        "description": "Tracks gem bundle purchases",
        "type": "number",
        "AI": true
    },
    "95": {
        "name": "Asset Management 95",
        "description": "Asset management and positioning coordinate constant",
        "type": "number",
        "AI": true
    },
    "96": {
        "name": "Accumulated Dilapidated Slush Days",
        "description": "Days of accumulated dilapidated slush",
        "type": "number"
    },
    "97": {
        "name": "Character Code A/NUMPAD_1",
        "description": "Character encoding for keyboard and numpad input",
        "type": "number",
        "AI": true
    },
    "98": {
        "name": "Accumulated Mutated Mush Days",
        "description": "Days of accumulated mutated mush",
        "type": "number"
    },
    "99": {
        "name": "Pen-pal Minigame Counter",
        "description": "Pen-pal minigame counter max bonus at 225",
        "type": "number"
    },
    "100": {
        "name": "W4 Spiceclaim counter",
        "description": "Daily counter for pet spiceclaims, starts at 0 to 100 and locks after that",
        "type": "number"
    },
    "101": {
        "name": "Killroy Crystals",
        "description": "Killroy crystals (minus value)",
        "type": "number"
    },
    "102": {
        "name": "Event Spawn Limiter",
        "description": "Caps daily special event spawns (e.g. Twitch events)",
        "type": "number",
        "AI": true
    },
    "103": {
        "name": "Lava Guide / Tutorial Progression",
        "description": "Tracks Lava tutorial/story stages (-2 to 7)",
        "type": "number"
    },
    "104": {
        "name": "Tutorial UI Toggle",
        "description": "Controls tutorial UI visibility (LavaTutStuff)",
        "type": "number",
        "AI": true
    },
    "105": {
        "name": "Killroy Skulls",
        "description": "Killroy skulls currency",
        "type": "number"
    },
    "106": {
        "name": "Killroy Upgrade - Timer",
        "description": "Killroy timer upgrade level",
        "type": "number"
    },
    "107": {
        "name": "Killroy Upgrade - Talent Drops",
        "description": "Killroy talent drops upgrade level",
        "type": "number"
    },
    "108": {
        "name": "Killroy Upgrade - Bonus Skulls",
        "description": "Killroy bonus skulls upgrade (do not set if not unlocked)",
        "type": "number",
        "warning": "Do not set if you haven't unlocked this upgrade yet"
    },
    "109": {
        "name": "Killroy Upgrade - Respawn",
        "description": "Killroy respawn upgrade (do not set if not unlocked)",
        "type": "number",
        "warning": "Do not set if you haven't unlocked this upgrade yet"
    },
    "110": {
        "name": "Killroy Upgrade - 5th",
        "description": "Killroy 5th upgrade (do not set if not unlocked)",
        "type": "number",
        "warning": "Do not set if you haven't unlocked this upgrade yet"
    },
    "111": {
        "name": "Killroy Upgrade - 6th",
        "description": "Killroy 6th upgrade (do not set if not unlocked)",
        "type": "number",
        "warning": "Do not set if you haven't unlocked this upgrade yet"
    },
    "112": {
        "name": "Killroy Runs Total",
        "description": "Total number of finished Killroy runs",
        "type": "number"
    },
    "113": {
        "name": "Killroy Wake Status",
        "description": "Set to 0 to wake up Killroy",
        "type": "number"
    },
    "114": {
        "name": "Talent Point System",
        "description": "Tracks/cycles talent point rewards",
        "type": "number",
        "AI": true
    },
    "115": {
        "name": "Killroy Airhorn Reset",
        "description": "Set to 0 to make airhorn reset available",
        "type": "number"
    },
    "116": {
        "name": "Vertex Buffer Index",
        "description": "Vertex buffer index and map identifier in rendering system",
        "type": "number",
        "AI": true
    },
    "117": {
        "name": "Boss Kill Achievement",
        "description": "Tracks major boss kills, unlocks breeding/classes",
        "type": "number",
        "AI": true
    },
    "118": {
        "name": "Town Popup for Gemshop",
        "description": "Controls town popup for gemshop",
        "type": "number"
    },
    "119": {
        "name": "Story Quest Completion",
        "description": "Tracks major story quests and world access",
        "type": "number",
        "AI": true
    },
    "120": {
        "name": "Idle Skilling Code Tracker",
        "description": "Tracks sequential code input for rewards",
        "type": "number",
        "AI": true
    },
    "121": {
        "name": "Next Idleskilling Codes Days",
        "description": "Days left for next idleskilling codes",
        "type": "number"
    },
    "122": {
        "name": "UI Inventory Management",
        "description": "UI inventory slot configurations and player preferences",
        "type": "number",
        "AI": true
    },
    "123": {
        "name": "Draconic Cauldrons",
        "description": "Number of draconic cauldrons for liquid cauldrons in alchemy",
        "type": "number"
    },
    "124": {
        "name": "Sailing Time Tracker",
        "description": "Tracks sailing activity time for display",
        "type": "number",
        "AI": true
    },
    "125": {
        "name": "3D Printer Days for Multi",
        "description": "3D printer days for multi artifact",
        "type": "number"
    },
    "126": {
        "name": "Gallery State Machine",
        "description": "4-mode gallery system state: 1=trophy, 2=trophy info, 3=nametag, 4=nametag info with toggle mechanisms",
        "type": "number"
    },
    "127": {
        "name": "Status Effect Timers & Graphics Data",
        "description": "Status effect countdown timers using Math.round(c.asNumber(_GenINFO[127]) + -1) + 3D vertex buffer graphics data",
        "type": "number"
    },
    "128": {
        "name": "UTF-8 Encoding & Graphics Constants",
        "description": "UTF-8 encoding threshold + 128x128 graphics dimensions + power-of-2 values for graphics efficiency + mode flags",
        "type": "number"
    },
    "129": {
        "name": "Gem Economy & Chest Spawn System",
        "description": "Gem shop purchase tracking → chest spawn mechanics using Math.ceil(GemItemsPurchased[129] / 3.5) with 120ms timer delay",
        "type": "number"
    },
    "130": {
        "name": "Skill Tree Tutorial Gate",
        "description": "Flag for tutorial completion/skill tree unlock",
        "type": "number",
        "AI": true
    },
    "131": {
        "name": "Silver Pen Tracker",
        "description": "Tracks accumulated silver pens from bonuses",
        "type": "number",
        "AI": true
    },
    "132": {
        "name": "Atom Collider Interface",
        "description": "Visual state control for Atom Collider UI",
        "type": "number",
        "AI": true
    },
    "133": {
        "name": "Atom Threshold Multiplier",
        "description": "Cycles threshold difficulty (0-3)",
        "type": "number",
        "AI": true
    },
    "134": {
        "name": "Hydrogen Bonus Stamp Days",
        "description": "Days of accumulated hydrogen bonus for stamp",
        "type": "number"
    },
    "135": {
        "name": "Current Daily Boron Clicks Left",
        "description": "Current daily boron clicks left",
        "type": "number"
    },
    "136": {
        "name": "UI Component Lava Message",
        "description": "Lava message",
        "type": "number"
    },
    "137": {
        "name": "Progression State Flag",
        "description": "Controls tutorial/dungeon access state",
        "type": "number",
        "AI": true
    },
    "138": {
        "name": "Divine Knight Orb Kill Count",
        "description": "Divine knight orb kill count (Divine Orb skill)",
        "type": "number"
    },
    "139": {
        "name": "Siege Breaker Flag Kill Count",
        "description": "Siege breaker flag kill count (Pirate Flag skill)",
        "type": "number"
    },
    "140": {
        "name": "Keybind: Move Up/W",
        "description": "Keycode for upward movement",
        "type": "number",
        "AI": true
    },
    "141": {
        "name": "Keybind: Move Down/S",
        "description": "Keycode for downward movement",
        "type": "number",
        "AI": true
    },
    "142": {
        "name": "Keybind: Move Left/A",
        "description": "Keycode for left movement",
        "type": "number",
        "AI": true
    },
    "143": {
        "name": "Keybind: Move Right/D",
        "description": "Keycode for right movement",
        "type": "number",
        "AI": true
    },
    "144": {
        "name": "Keybind: Action/E",
        "description": "Keycode for action/interact",
        "type": "number",
        "AI": true
    },
    "145": {
        "name": "Keybind: Special/R",
        "description": "Keycode for special action",
        "type": "number",
        "AI": true
    },
    "146": {
        "name": "Keybind Display: Up/W",
        "description": "Display string for Up key",
        "type": "string",
        "AI": true
    },
    "147": {
        "name": "Keybind Display: Down/S",
        "description": "Display string for Down key",
        "type": "string",
        "AI": true
    },
    "148": {
        "name": "Keybind Display: Left/A",
        "description": "Display string for Left key",
        "type": "string",
        "AI": true
    },
    "149": {
        "name": "Keybind Display: Right/D",
        "description": "Display string for Right key",
        "type": "string",
        "AI": true
    },
    "150": {
        "name": "Keybind Display: Action/E",
        "description": "Display string for Action key",
        "type": "string",
        "AI": true
    },
    "151": {
        "name": "Keybind Display: Special/R",
        "description": "Display string for Special key",
        "type": "string",
        "AI": true
    },
    "152": {
        "name": "Mage Kill Count",
        "description": "Mage kill count (Wormhole skill)",
        "type": "number"
    },
    "153": {
        "name": "Language Selection",
        "description": "Selected language index (1-7)",
        "type": "number",
        "AI": true
    },
    "154": {
        "name": "95% Stamp Cost Reduction",
        "description": "95% stamp cost reduction amount",
        "type": "number"
    },
    "155": {
        "name": "Card Level Override",
        "description": "Comma-separated Card IDs forced to level 6",
        "type": "string",
        "AI": true
    },
    "156": {
        "name": "5-Star Cardifiers",
        "description": "Number of 5-star cardifiers",
        "type": "number"
    },
    "157": {
        "name": "Player Auto-Move",
        "description": "Toggle for player auto-movement (1=On)",
        "type": "number",
        "AI": true
    },
    "158": {
        "name": "Void Man Portals Cleared",
        "description": "Void man portals cleared highscore (for talent calculations)",
        "type": "number"
    },
    "159": {
        "name": "Sailing/Gem Init Flag",
        "description": "One-time initialization flag (Set to 1)",
        "type": "number",
        "AI": true
    },
    "160": {
        "name": "Uncollected Garbage (Ground)",
        "description": "Uncollected garbage on the ground",
        "type": "number"
    },
    "161": {
        "name": "Garbage Currency",
        "description": "Garbage currency in Fishing Islands",
        "type": "number"
    },
    "162": {
        "name": "Bottles Currency",
        "description": "Bottles currency in Fishing Islands",
        "type": "number"
    },
    "163": {
        "name": "Garbage Island - % Garbage",
        "description": "Garbage Island upgrade (+% Garbage)",
        "type": "number"
    },
    "164": {
        "name": "Garbage Island - % Bottles",
        "description": "Garbage Island upgrade (+% Bottles)",
        "type": "number"
    },
    "165": {
        "name": "Emporium Bonus Bribe",
        "description": "Controls premium bribe features for fishing islands",
        "type": "number",
        "AI": true
    },
    "166": {
        "name": "Rando Island - % Loot",
        "description": "Rando Island upgrade (+% Loot - all random events)",
        "type": "number"
    },
    "167": {
        "name": "Rando Island - Double Boss",
        "description": "Rando Island upgrade (+% for Double Boss)",
        "type": "number"
    },
    "168": {
        "name": "Graphics Rendering Index",
        "description": "Graphics rendering pipeline, vertex buffer operations and font rendering",
        "type": "number",
        "AI": true
    },
    "169": {
        "name": "Unlocked Islands",
        "description": "Unlocked islands (all islands: 'abcde_')",
        "type": "string"
    },
    "170": {
        "name": "Uncollected Bottles (Docks)",
        "description": "Uncollected bottles in the docks",
        "type": "number"
    },
    "171": {
        "name": "Temp Bottle Collection",
        "description": "Temporary bottle counter with scaling logic",
        "type": "number",
        "AI": true
    },
    "172": {
        "name": "Shimmer Island Dummy DPS",
        "description": "Shimmer Island dummy DPS",
        "type": "number"
    },
    "173": {
        "name": "Shimmers Currency",
        "description": "Shimmers currency in Fishing Islands",
        "type": "number"
    },
    "174": {
        "name": "Shimmer Island - Base STR",
        "description": "Shimmer Island upgrade (+ Base STR)",
        "type": "number"
    },
    "175": {
        "name": "Shimmer Island - Base AGI",
        "description": "Shimmer Island upgrade (+ Base AGI)",
        "type": "number"
    },
    "176": {
        "name": "Shimmer Island - Base WIS",
        "description": "Shimmer Island upgrade (+ Base WIS)",
        "type": "number"
    },
    "177": {
        "name": "Shimmer Island - Base LUK",
        "description": "Shimmer Island upgrade (+ Base LUK)",
        "type": "number"
    },
    "178": {
        "name": "Shimmer Island - % Total Damage",
        "description": "Shimmer Island upgrade (+% Total Damage)",
        "type": "number"
    },
    "179": {
        "name": "Shimmer Island - % Class EXP",
        "description": "Shimmer Island upgrade (+% Class EXP)",
        "type": "number"
    },
    "180": {
        "name": "Shimmer Island - % Skill Eff",
        "description": "Shimmer Island upgrade (+% Skill Eff)",
        "type": "number"
    },
    "181": {
        "name": "Shimmer Island Trial Damage",
        "description": "Shimmer Island trial damage",
        "type": "number"
    },
    "182": {
        "name": "Shimmer Trial Flag",
        "description": "Binary flag (0/1) for trial completion",
        "type": "number",
        "AI": true
    },
    "183": {
        "name": "Weekly DPS Challenge",
        "description": "Selector (0-21) for weekly DPS challenge",
        "type": "number",
        "AI": true
    },
    "184": {
        "name": "Fractal Isle AFK Time",
        "description": "Fractal isle AFK time",
        "type": "number"
    },
    "185": {
        "name": "WeeklyBoss Player Turn",
        "description": "Tracks which player's turn it is in WeeklyBoss",
        "type": "number",
        "AI": true
    },
    "186": {
        "name": "W2 Town Boss Damage",
        "description": "Damage done to W2 town boss",
        "type": "number"
    },
    "187": {
        "name": "W2 Town Boss Status",
        "description": "W2 town boss status (5=dead, 0-4=alive)",
        "type": "number"
    },
    "188": {
        "name": "Trophy Currency",
        "description": "Trophy currency for W2 town boss",
        "type": "number"
    },
    "189": {
        "name": "Max W2 Town Weekly Boss Skulls",
        "description": "Max W2 town weekly boss skulls reached (up to 5)",
        "type": "number"
    },
    "190": {
        "name": "W2 Town Boss Attempt Reset",
        "description": "Set to 0 to make reset available",
        "type": "number"
    },
    "191": {
        "name": "WeeklyBoss Timer",
        "description": "Weekly timer tracking for boss rotation",
        "type": "number",
        "AI": true
    },
    "192": {
        "name": "Amount of Gold Nuggets dug since last max in Gaming",
        "description": "Amount of Gold Nugget dug since last max in Gaming",
        "type": "number"
    },
    "193": {
        "name": "Game Progression Array",
        "description": "Game progression array for kill tracking and advancement",
        "type": "number",
        "AI": true
    },
    "194": {
        "name": "Kill Advance Condition",
        "description": "Condition for advancing after kills",
        "type": "number",
        "AI": true
    },
    "195": {
        "name": "Gem Drop Counter Limit",
        "description": "Maximum limit for gem drop counters",
        "type": "number",
        "AI": true
    },
    "196": {
        "name": "UI Control & Portal Positioning",
        "description": "UI control foundation + wisdom calculations + portal positioning + game progression tracking with graphics integration",
        "type": "number",
        "AI": true
    },
    "197": {
        "name": "Tome UI & Wisdom Card Management",
        "description": "Tome UI control + hole wisdom card management + dual interface system with N[127] coordination",
        "type": "number",
        "AI": true
    },
    "198": {
        "name": "Most Money held in Storage (Tome)",
        "description": "Money tracking + tome inventory + companions system + card management with vertex buffer operations",
        "type": "number"
    },
    "199": {
        "name": "Jackpots Counter in Arcade (Tome)",
        "description": "Tracks the number of jackpots collected in Arcade",
        "type": "number"
    },
    "200": {
        "name": "Highest Drop rarity Multi (Tome)",
        "description": "Tracks the highest drop rarity multiplier",
        "type": "number"
    },
    "201": {
        "name": "Best Spiketrap Surprise round (Tome)",
        "description": "Tracks rounds in spike game logic",
        "type": "number"
    },
    "202": {
        "name": "Crystal Spawn Tracking (Tome)",
        "description": "Average kills for a Crystal Spawn",
        "type": "number"
    },
    "203": {
        "name": "Most DMG Dealt to Gravestone in a Weekly Battle (Tome)",
        "description": "Most DMG Dealt to Gravestone in a Weekly Battle",
        "type": "number"
    },
    "204": {
        "name": "Killroy Kills - Melee (Tome)",
        "description": "Killroy kills for melee classes",
        "type": "number"
    },
    "205": {
        "name": "Killroy Kills - Ranged (Tome)",
        "description": "Killroy kills for ranged classes",
        "type": "number"
    },
    "206": {
        "name": "Killroy Kills - Magic (Tome)",
        "description": "Killroy kills for magic classes",
        "type": "number"
    },
    "207": {
        "name": "Boss Kill Timer Chaotic Efaunt (Tome)",
        "description": "Fastest Time to kill Chaotic Efaunt (in Seconds)",
        "type": "number"
    },
    "208": {
        "name": "Most Spore Caps held in Inventory at once (Tome)",
        "description": "Tracks the most spore caps held in inventory at once",
        "type": "number"
    },
    "209": {
        "name": "Best Non Duplicate Goblin Gorefest Wave (Tome)",
        "description": "Tracks the best non-duplicate goblin gorefest wave",
        "type": "number"
    },
    "210": {
        "name": "Highest Immortal Snail LV (Tome)",
        "description": "Tracks the highest level of an immortal snail in Gaming",
        "type": "number"
    },
    "211": {
        "name": "OakTree 3D Sampling Data (Tome)",
        "description": "Sampling data for OakTree",
        "type": "number"
    },
    "212": {
        "name": "Copper 3D Sampling Data (Tome)",
        "description": "Sampling data for Copper",
        "type": "number"
    },
    "213": {
        "name": "Spore 3D Sampling Data (Tome)",
        "description": "Sampling data for Grasslands1",
        "type": "number"
    },
    "214": {
        "name": "Goldfish 3D Sampling Data (Tome)",
        "description": "Sampling data for Fish1",
        "type": "number"
    },
    "215": {
        "name": "Fly 3D Sampling Data (Tome)",
        "description": "Sampling data for Bug1",
        "type": "number"
    },
    "216": {
        "name": "Nametags Found (Tome) (Unsure)",
        "description": "Tracks the number of nametags found",
        "type": "number"
    },
    "217": {
        "name": "Most Giants Killed in a Single Week (Tome)",
        "description": "Tracks the most giants killed in a single week",
        "type": "number"
    },
    "218": {
        "name": "Fastest Time to Kill 200 Tremor Wurms (Tome)",
        "description": "Tracks the fastest time to kill 200 Tremor Wurms",
        "warning": "The Tome system uses 1000 - this value",
        "type": "number"
    },
    "219": {
        "name": "Highest Crop OG (Tome)",
        "description": "Highest crop OG level achieved",
        "warning": "The Tome system uses 2^this value as the actual value",
        "type": "number"
    },
    "220": {
        "name": "Fastest Time reaching Round 100 Arena (Tome)",
        "description": "Tracks the fastest time to reach round 100 in Arena",
        "warning": "The Tome system uses 1000 - this value",
        "type": "number"
    },
    "221": {
        "name": "Largest Magic Bean Trade (Tome)",
        "description": "Maximum beans obtained in single trade",
        "type": "number"
    },
    "222": {
        "name": "Most Balls earned from LBoFaF (Tome)",
        "description": "Tracks the most balls earned from LBoFaF",
        "type": "number"
    },
    "223": {
        "name": "Tome State Flag",
        "description": "State/quality level of Tome system",
        "type": "number",
        "AI": true
    },
    "224": {
        "name": "Most Greenstacks in Storage (Tome)",
        "description": "Tracks the most greenstacks in storage",
        "type": "number"
    },
    "225": {
        "name": "Accumulated W5 Miniboss Days",
        "description": "Tracks the accumulated w5 miniboss days",
        "type": "number"
    },
    "226": {
        "name": "Accumulated W6 Miniboss Days",
        "description": "Tracks the accumulated w6 miniboss days",
        "type": "number"
    },
    "227": {
        "name": "Skull Shop Event Flag",
        "description": "Single-use event trigger for skull shop",
        "type": "number",
        "AI": true
    },
    "228": {
        "name": "Skull Shop Counter 1",
        "description": "Progressive counter for skull shop reward tier 1",
        "type": "number",
        "AI": true
    },
    "229": {
        "name": "Skull Shop Counter 2",
        "description": "Progressive counter for skull shop reward tier 2",
        "type": "number",
        "AI": true
    },
    "230": {
        "name": "Skull Shop Counter 3",
        "description": "Progressive counter for skull shop reward tier 3",
        "type": "number",
        "AI": true
    },
    "231": {
        "name": "Ninja Floors System",
        "description": "Tracks current floor progression in ninja system",
        "type": "number",
        "AI": true
    },
    "232": {
        "name": "Multi-System Bonus Calc",
        "description": "Master bonus multiplier for talents/damage/drops",
        "type": "number",
        "AI": true
    },
    "233": {
        "name": "Sneaking Gems 1 counter",
        "description": "Sneaking Gems counter",
        "type": "number"
    },
    "234": {
        "name": "Sneaking Gems 2 counter",
        "description": "Sneaking Gems counter",
        "type": "number"
    },
    "235": {
        "name": "Sneaking Gems 3 counter",
        "description": "Sneaking Gems counter",
        "type": "number"
    },
    "236": {
        "name": "Sneaking Gems 4 counter",
        "description": "Sneaking Gems counter",
        "type": "number"
    },
    "237": {
        "name": "Sneaking Gems 5 counter",
        "description": "Sneaking Gems counter",
        "type": "number"
    },
    "238": {
        "name": "Sneaking Gems 6 counter",
        "description": "Sneaking Gems counter",
        "type": "number"
    },
    "239": {
        "name": "Sneaking Gems 7 counter",
        "description": "Sneaking Gems counter",
        "type": "number"
    },
    "240": {
        "name": "Sneaking Gems 8 counter",
        "description": "Sneaking Gems counter",
        "type": "number"
    },
    "241": {
        "name": "Time Tracking System",
        "description": "Time-based achievement progress tracking",
        "type": "number",
        "AI": true
    },
    "242": {
        "name": "Hoops High Score",
        "description": "Tracks best score in hoops game",
        "type": "number"
    },
    "243": {
        "name": "Hoops State Manager",
        "description": "Manages hoops game availability/cooldown",
        "type": "number",
        "AI": true
    },
    "244": {
        "name": "Basketball Achievement",
        "description": "Unlocks basketball activity after level 20",
        "type": "number",
        "AI": true
    },
    "245": {
        "name": "Hoops Party Unlock",
        "description": "Tracks party-based hoops game unlock",
        "type": "number",
        "AI": true
    },
    "246": {
        "name": "Tutorial Progress",
        "description": "Tracks tutorial completion and milestones",
        "type": "number",
        "AI": true
    },
    "247": {
        "name": "NPC Interaction Visible",
        "description": "Controls NPC interaction visibility",
        "type": "number",
        "AI": true
    },
    "248": {
        "name": "Mr. Pigibank Visible",
        "description": "Controls Mr. Pigibank NPC appearance",
        "type": "number",
        "AI": true
    },
    "249": {
        "name": "UI Interaction Visible",
        "description": "Controls UI element visibility states",
        "type": "number",
        "AI": true
    },
    "250": {
        "name": "Town_Marble Tracking",
        "description": "Controls Town_Marble NPC and kill tracking",
        "type": "number",
        "AI": true
    },
    "251": {
        "name": "Grasslands_Gary Visible",
        "description": "Controls Grasslands_Gary NPC appearance",
        "type": "number",
        "AI": true
    },
    "252": {
        "name": "Toggle for steam midweek madness gift bundle",
        "description": "Toggle for steam midweek madness gift bundle",
        "type": "number"
    },
    "253": {
        "name": "Orion - Feathers",
        "description": "Orion the Great Horned Owl feathers",
        "type": "number"
    },
    "254": {
        "name": "Orion - Feather Generation",
        "description": "Orion upgrade (Feather Generation)",
        "type": "number"
    },
    "255": {
        "name": "Orion - Bonuses",
        "description": "Orion upgrade (Bonuses of Orion) - permanent bonus value",
        "type": "number",
        "warning": "Keep reasonable like 70-90"
    },
    "256": {
        "name": "Orion - Feather Multiplier",
        "description": "Orion upgrade (Feather Multiplier)",
        "type": "number"
    },
    "257": {
        "name": "Orion - Feather Cheapener",
        "description": "Orion upgrade (Feather Cheapener)",
        "type": "number"
    },
    "258": {
        "name": "Orion - Feather Restart",
        "description": "Orion upgrade (Feather Restart)",
        "type": "number",
        "warning": "Keep reasonable like 30-40"
    },
    "259": {
        "name": "Orion - Super Feather Production",
        "description": "Orion upgrade (Super Feather Production)",
        "type": "number"
    },
    "260": {
        "name": "Orion - Shiny Feathers",
        "description": "Orion upgrade (Shiny Feathers)",
        "type": "number"
    },
    "261": {
        "name": "Orion - Super Feather Cheapener",
        "description": "Orion upgrade (Super Feather Cheapener)",
        "type": "number"
    },
    "262": {
        "name": "Orion - Great Mega Reset",
        "description": "Orion upgrade (The Great Mega Reset) - permanent bonus value",
        "type": "number",
        "warning": "Keep reasonable like 70-90"
    },
    "263": {
        "name": "Orion - Unknown Feathers",
        "description": "Related to feathers (probably bar fill)",
        "type": "number"
    },
    "264": {
        "name": "Orion - Shiny Feathers Amount",
        "description": "Orion shiny feathers amount",
        "type": "number"
    },
    "265": {
        "name": "Orion Complete Flag",
        "description": "Orion system completion flag/Map 42 unlock",
        "type": "number",
        "AI": true
    },
    "266": {
        "name": "Poppy Complete Flag",
        "description": "Poppy system completion flag/Map 73 unlock",
        "type": "number",
        "AI": true
    },
    "267": {
        "name": "Poppy - Fish Amount",
        "description": "Poppy the Kangaroo fish amount (can use exponent like '5e+50')",
        "type": "string"
    },
    "268": {
        "name": "Poppy - Tasty Fishbait",
        "description": "Poppy upgrade (Tasty Fishbait)",
        "type": "number"
    },
    "269": {
        "name": "Poppy - Quick Reeling",
        "description": "Poppy upgrade (Quick Reeling)",
        "type": "number"
    },
    "270": {
        "name": "Poppy - Shiny Lure",
        "description": "Poppy upgrade (Shiny Lure)",
        "type": "number"
    },
    "271": {
        "name": "Poppy - Bonuses",
        "description": "Poppy upgrade (Bonuses from Poppy) - permanent bonus value",
        "type": "number",
        "warning": "Keep reasonable like 70-90"
    },
    "272": {
        "name": "Poppy - Fishy Discount",
        "description": "Poppy upgrade (Fishy Discount)",
        "type": "number"
    },
    "273": {
        "name": "Poppy - Juicy Worm",
        "description": "Poppy upgrade (Juicy Worm)",
        "type": "number"
    },
    "274": {
        "name": "Poppy - Fishero Reset",
        "description": "Poppy upgrade (Fishero Reset)",
        "type": "number",
        "warning": "Keep reasonable like 30-40"
    },
    "275": {
        "name": "Poppy - Fishing Buddy",
        "description": "Poppy upgrade (Fishing Buddy)",
        "type": "number"
    },
    "276": {
        "name": "Poppy - Lightning Quickness",
        "description": "Poppy upgrade (Lightning Quickness)",
        "type": "number"
    },
    "277": {
        "name": "Poppy - Fisheroo Investing",
        "description": "Poppy upgrade (Fisheroo Investing)",
        "type": "number"
    },
    "278": {
        "name": "Poppy - Multihook Fishing",
        "description": "Poppy upgrade (Multihook Fishing)",
        "type": "number"
    },
    "279": {
        "name": "Poppy - Greatest Catch",
        "description": "Poppy upgrade (Greatest Catch) - needs to be +12, Counts all other 11 fishes in this value",
        "type": "number"
    },
    "280": {
        "name": "Roo Progress Tracker",
        "description": "Tracks Roo system upgrade progress",
        "type": "number",
        "AI": true
    },
    "281": {
        "name": "Poppy - Fish (Yellow)",
        "description": "Poppy yellow fish amount",
        "type": "number"
    },
    "282": {
        "name": "Poppy - Fish (Red)",
        "description": "Poppy red fish amount",
        "type": "number"
    },
    "283": {
        "name": "Poppy - Fish (Green)",
        "description": "Poppy green fish amount",
        "type": "number"
    },
    "284": {
        "name": "Poppy - Fish (Purple)",
        "description": "Poppy purple fish amount",
        "type": "number"
    },
    "285": {
        "name": "Poppy - Fish (Silver)",
        "description": "Poppy silver fish amount",
        "type": "number"
    },
    "286": {
        "name": "Poppy - Fish (Blue)",
        "description": "Poppy blue fish amount",
        "type": "number"
    },
    "287": {
        "name": "Roo Mode Flag",
        "description": "Toggles normal vs Megafish mode",
        "type": "number",
        "AI": true
    },
    "288": {
        "name": "Roo Catch Progress",
        "description": "Tracks progress toward next Roo catch",
        "type": "number",
        "AI": true
    },
    "289": {
        "name": "Roo Silver Catch Progress",
        "description": "Tracks silver tier Roo catch progress",
        "type": "number",
        "AI": true
    },
    "290": {
        "name": "Poppy - Reset Points",
        "description": "Poppy reset points amount",
        "type": "number"
    },
    "291": {
        "name": "Poppy - Reset Points (Blue)",
        "description": "Poppy reset points upgrades (blue)",
        "type": "number"
    },
    "292": {
        "name": "Poppy - Reset Points (Yellow)",
        "description": "Poppy reset points upgrades (yellow)",
        "type": "number"
    },
    "293": {
        "name": "Poppy - Reset Points (Green)",
        "description": "Poppy reset points upgrades (green)",
        "type": "number"
    },
    "294": {
        "name": "Poppy - Reset Points (Red)",
        "description": "Poppy reset points upgrades (red)",
        "type": "number"
    },
    "295": {
        "name": "Poppy - Reset Points (Silver)",
        "description": "Poppy reset points upgrades (silver)",
        "type": "number"
    },
    "296": {
        "name": "Poppy - Tartar Amount",
        "description": "Poppy Tar pit tartar amount",
        "type": "number"
    },
    "297": {
        "name": "Poppy - Super Yummy Bait",
        "description": "Poppy Tar pit upgrade (Super Yummy Bait)",
        "type": "number"
    },
    "298": {
        "name": "Poppy - Bonus Catching",
        "description": "Poppy Tar pit upgrade (Bonus Catching)",
        "type": "number"
    },
    "299": {
        "name": "Poppy - Bluefin Frenzy",
        "description": "Poppy Tar pit upgrade (Bluefin Frenzy)",
        "type": "number"
    },
    "300": {
        "name": "Poppy - Fishy Reductions",
        "description": "Poppy Tar pit upgrade (Fishy Reductions)",
        "type": "number"
    },
    "301": {
        "name": "Poppy - Super Tarbait",
        "description": "Poppy Tar pit upgrade (Super Tarbait)",
        "type": "number"
    },
    "302": {
        "name": "Poppy - Tarrific Resets",
        "description": "Poppy Tar pit upgrade (Tarrific Resets)",
        "type": "number"
    },
    "303": {
        "name": "Poppy - Mongo Multipliers",
        "description": "Poppy Tar pit upgrade (Mongo Multipliers)",
        "type": "number"
    },
    "304": {
        "name": "Poppy - King Worm",
        "description": "Poppy Tar pit upgrade (King Worm)",
        "type": "number"
    },
    "305": {
        "name": "Poppy - Tartar Progress",
        "description": "Poppy Tar pit tartar fishing progress bar (0-100)",
        "type": "number"
    },
    "306": {
        "name": "Farming Autofeeder",
        "description": "Toggle for automated resource feeding",
        "type": "number",
        "AI": true
    },
    "307": {
        "name": "Farming Reset Flag",
        "description": "Tracks reset state for farming upgrades",
        "type": "number",
        "AI": true
    },
    "308": {
        "name": "Voting Selection",
        "description": "Tracks weekly community voting choice",
        "type": "number",
        "AI": true
    },
    "309": {
        "name": "Voting Week Tracker",
        "description": "Tracks current voting week cycle",
        "type": "number",
        "AI": true
    },
    "310": {
        "name": "Event Points",
        "description": "Event points (as displayed in account info)",
        "type": "number"
    },
    "311": {
        "name": "Event Bonuses",
        "description": "Tracks event bonuses, Set to '0abc_defghijkmlopn' to apply all (up to 4th Anniversary)",
        "type": "string"
    },
    "312": {
        "name": "Villager Selection Tracking",
        "description": "Part of Villager management system, tracks selected villager and increments selection count",
        "type": "number",
        "AI": true
    },
    "313": {
        "name": "Villager Action Flag",
        "description": "Set to 1 when villager actions are available; controls UI display conditions for villager interactions",
        "type": "number",
        "AI": true
    },
    "314": {
        "name": "Coordinate/Length Value",
        "description": "Used as X/Y coordinate for portal positioning and in monster/scene element placement calculations",
        "type": "number",
        "AI": true
    },
    "315": {
        "name": "Daily Reset Trigger",
        "description": "Manages time-based daily reset logic",
        "type": "number",
        "AI": true
    },
    "316": {
        "name": "Combat System Flag",
        "description": "Generic combat state flag",
        "type": "number",
        "AI": true
    },
    "317": {
        "name": "Daily Event Counter",
        "description": "Monitors daily event participation",
        "type": "number",
        "AI": true
    },
    "318": {
        "name": "Daily Hole Resources Destroyed",
        "description": "Daily number of resource nodes in the Hole destroyed (max 5)",
        "type": "number"
    },
    "319": {
        "name": "Endless Summoning Level",
        "description": "Current endless summoning level",
        "type": "number",
        "warning": "Does not provide associated win rewards"
    },
    "320": {
        "name": "Equinox Pengy Count",
        "description": "Number of equinox pengy (can be increased above 5)",
        "type": "number"
    },
    "321": {
        "name": "Endless Summoning High Performance",
        "description": "Endless summoning high performance toggle",
        "type": "number"
    },
    "322": {
        "name": "Popup Cooldown Timer",
        "description": "Controls gem/bundle popup display intervals",
        "type": "number",
        "AI": true
    },
    "323": {
        "name": "Supreme Wiring Bonus Days",
        "description": "Accumulated days of Supreme Wiring Bonus (safe to max at 50)",
        "type": "number"
    },
    "324": {
        "name": "Cosmic Balls",
        "description": "Number of Cosmic Balls",
        "type": "number"
    },
    "325": {
        "name": "Event Tries Left",
        "description": "Event (Valentines, Anniversaries...) tries left",
        "type": "number"
    },
    "326": {
        "name": "Daily Event Tries Gem Purchases",
        "description": "Cap of daily Event tries gem purchases (set to 0 to purchase again)",
        "type": "number"
    },
    "327": {
        "name": "Quest93 Drop Prevention",
        "description": "Flag for Quest93 drop prevention",
        "type": "number",
        "AI": true
    },
    "328": {
        "name": "Worship Totem Calculation Factor",
        "description": "Used as a key ('_Plunderous_Kills') in the achievement system and as a division factor in worship/trial calculations (stores Meal Bonus)",
        "type": "number",
        "AI": true
    },
    "329": {
        "name": "Grimoire - total bones collected",
        "description": "Accumulated total bones from Grimoire Wraith",
        "type": "number"
    },
    "330": {
        "name": "Grimoire - current bone1 (femur)",
        "description": "Current bone1 (femur) from Grimoire Wraith",
        "type": "number"
    },
    "331": {
        "name": "Grimoire - current bone2 (ribcage)",
        "description": "Current bone2 (ribcage) from Grimoire Wraith",
        "type": "number"
    },
    "332": {
        "name": "Grimoire - current bone3 (cranium)",
        "description": "Current bone3 (cranium) from Grimoire Wraith",
        "type": "number"
    },
    "333": {
        "name": "Grimoire - current bone4 (bovinae)",
        "description": "Current bone4 (bovinae) from Grimoire Wraith",
        "type": "number"
    },
    "334": {
        "name": "Grimoire - knockout! level",
        "description": "",
        "type": "number"
    },
    "335": {
        "name": "Grimoire - elimination! level",
        "description": "",
        "type": "number"
    },
    "336": {
        "name": "Grimoire - annihilation! level",
        "description": "",
        "type": "number"
    },
    "337": {
        "name": "Ribbon Shelf/Event Activation Flag",
        "description": "Tracks Ribbon Shelf unlock status and is set to 1 when a specific server event (e.g., 'ValOn') is active",
        "type": "number",
        "AI": true
    },
    "338": {
        "name": "Vault Knockout Progress",
        "description": "Tracks knockout achievements for Vault upgrades",
        "type": "number",
        "AI": true
    },
    "339": {
        "name": "Tutorial Hint Dismissal Flag",
        "description": "Tracks tutorial hints/prompts; set to 1 upon interaction to dismiss the hint UI",
        "type": "number",
        "AI": true
    },
    "340": {
        "name": "Total Ores Mined",
        "description": "Accumulated total ores for bonuses",
        "type": "number",
        "AI": true
    },
    "341": {
        "name": "New Character Tutorial Flag",
        "description": "Flag for new character tutorial display",
        "type": "number",
        "AI": true
    },
    "342": {
        "name": "Gaming Mutation Mechanics",
        "description": "Gaming mutation mechanics and probability calculations",
        "type": "number",
        "AI": true
    },
    "343": {
        "name": "Chest View Mode",
        "description": "Toggle for chest view display mode",
        "type": "number",
        "AI": true
    },
    "344": {
        "name": "Event Wheel Counter spins until event pity",
        "description": "Remaining spins until event pity",
        "type": "number"
    },
    "345": {
        "name": "Fish Caught Counter upgrade vault - schoolin the fish",
        "description": "Cumulative fish caught for bonuses",
        "type": "number"
    },
    "346": {
        "name": "Bugs Caught Counter upgrade vault - bug power en masse",
        "description": "Cumulative bugs caught for bonuses",
        "type": "number"
    },
    "347": {
        "name": "Delivery System Bonus",
        "description": "Delivery box system tracking and bonus",
        "type": "number",
        "AI": true
    },
    "348": {
        "name": "Talent Reset Counter",
        "description": "Tracks daily talent point resets",
        "type": "number",
        "AI": true
    },
    "349": {
        "name": "Menu Navigation State",
        "description": "Manages multi-state menu navigation",
        "type": "number",
        "AI": true
    },
    "350": {
        "name": "Companion System Toggle",
        "description": "Toggles companion system UI modes",
        "type": "number",
        "AI": true
    },
    "351": {
        "name": "Companion Selection Mode",
        "description": "Controls companion selection interface",
        "type": "number",
        "AI": true
    },
    "352": {
        "name": "Quest Completion Flag",
        "description": "One-time quest completion tracking",
        "type": "number",
        "AI": true
    },
    "353": {
        "name": "Hidden Wisdom Minigame High Score",
        "description": "Hidden wisdom minigame high score",
        "type": "number"
    },
    "354": {
        "name": "Companion Bonus Multi",
        "description": "Companion system bonus tracker (Cap 100)",
        "type": "number",
        "AI": true
    },
    "355": {
        "name": "Rupie Slugs Purchased",
        "description": "Number of rupie slugs purchased",
        "type": "number"
    },
    "356": {
        "name": "Grimoire DMG Tracker",
        "description": "Tracks peak Grimoire damage achieved",
        "type": "number",
        "AI": true
    },
    "357": {
        "name": "Compass - Dust Type 0 (stardust) Counter",
        "description": "Accumulated Dust Type 0 drops",
        "type": "number"
    },
    "358": {
        "name": "Compass - Dust Type 1 (moondust) Counter",
        "description": "Accumulated Dust Type 1 drops",
        "type": "number"
    },
    "359": {
        "name": "Compass - Dust Type 2 (solardust) Counter",
        "description": "Accumulated Dust Type 2 drops",
        "type": "number"
    },
    "360": {
        "name": "Compass - Dust Type 3 (cooldust) Counter",
        "description": "Accumulated Dust Type 3 drops",
        "type": "number"
    },
    "361": {
        "name": "Compass - Dust Type 4 (novadust) Counter",
        "description": "Accumulated Dust Type 4 drops",
        "type": "number"
    },
    "362": {
        "name": "Compass - Total Dust Accumulator",
        "description": "Aggregates all dust types for global calcs",
        "type": "number"
    },
    "363": {
        "name": "Magnesium, days stacked for critter bonus",
        "description": "Trapping upgrade/bonus tracker (Cap 60)",
        "type": "number"
    },
    "364": {
        "name": "Moon of Print, days stacked for printer bonus",
        "description": "Windwalker Compass ultimate bonus (Cap 100)",
        "type": "number"
    },
    "365": {
        "name": "Top of Morning count - daily kill count on windwalker for TOTM",
        "description": "Counter for Windwalker/Compass Tempest system",
        "type": "number"
    },
    "366": {
        "name": "Gem shop exalt stamps purchased",
        "description": "Base/purchased count of Stamp Doublers (7 max as of 21.11.2025)",
        "type": "number"
    },
    "367": {
        "name": "Charred Bones enabled (AFK deathbringer)",
        "description": "Charred Bones enabled (AFK deathbringer)",
        "type": "number"
    },
    "368": {
        "name": "Emperor Interface State",
        "description": "Boolean flag for emperor interface visibility",
        "type": "number",
        "AI": true
    },
    "369": {
        "name": "Emperor Showdown Level",
        "description": "Emperor Showdown Level (value+1 is current showdown)",
        "type": "number"
    },
    "370": {
        "name": "Emperor Entries Left",
        "description": "Entries left for Emperor (negative number, goes up to 0)",
        "type": "number"
    },
    "371": {
        "name": "UI Inventory Expansion",
        "description": "Stores reference to inventory expansion UI image, dynamically calculated based on owned inventory slots",
        "type": "number"
    },
    "372": {
        "name": "Achievement Progress Tracker",
        "description": "Achievement system tracking for progression monitoring",
        "type": "number",
        "AI": true
    },
    "373": {
        "name": "Game State Achievement Flag",
        "description": "Game state flag for achievement system",
        "type": "number",
        "AI": true
    },
    "374": {
        "name": "Achievement Unlock Condition",
        "description": "Achievement unlock condition tracking",
        "type": "number",
        "AI": true
    },
    "375": {
        "name": "Achievement Completion State",
        "description": "Achievement completion state monitoring",
        "type": "number",
        "AI": true
    },
    "376": {
        "name": "Achievement System Variable",
        "description": "General achievement system variable for tracking",
        "type": "number",
        "AI": true
    },
    "377": {
        "name": "Achievement Calculation Parameter",
        "description": "Calculation parameter used in achievement processing",
        "type": "number",
        "AI": true
    },
    "378": {
        "name": "Actor Y-Coordinate System",
        "description": "Y-coordinate parameter in actor creation system (used in createRecycledActor)",
        "type": "number",
        "AI": true
    },
    "379": {
        "name": "Armor Set Smithy Sets Unlocked",
        "description": "Armor Set Smithy sets unlocked",
        "type": "string"
    },
    "380": {
        "name": "Armor Set Smithy Unlocked",
        "description": "Armor Set Smithy unlocked (set to 1)",
        "type": "number"
    },
    "381": {
        "name": "Smithy 30-Day Counter",
        "description": "Day counter for smithy time-gating",
        "type": "number",
        "AI": true
    },
    "382": {
        "name": "Lifetime FOMO Tickets",
        "description": "Lifetime tickets bought from FOMO shop",
        "type": "number"
    },
    "383": {
        "name": "Prisma Bubbles",
        "description": "Prisma bubbles amount",
        "type": "number"
    },
    "384": {
        "name": "Selected Prisma Bubbles Index",
        "description": "Index of selected prisma bubbles",
        "type": "number"
    },
    "385": {
        "name": "Treasure Hunt Event ID",
        "description": "Tracks current treasure hunt event ID",
        "type": "number",
        "AI": true
    },
    "386": {
        "name": "Treasure Hunt Count",
        "description": "Tracks found treasures (limit 25)",
        "type": "number",
        "AI": true
    },
    "387": {
        "name": "Windwalker Restriction",
        "description": "Restriction flag for Windwalker class",
        "type": "number",
        "AI": true
    },
    "388": {
        "name": "Tachyon 1",
        "description": "Tachyon 1 amount",
        "type": "number"
    },
    "389": {
        "name": "Tachyon 2",
        "description": "Tachyon 2 amount",
        "type": "number"
    },
    "390": {
        "name": "Tachyon 3",
        "description": "Tachyon 3 amount",
        "type": "number"
    },
    "391": {
        "name": "Tachyon 4",
        "description": "Tachyon 4 amount",
        "type": "number"
    },
    "392": {
        "name": "Tachyon 5",
        "description": "Tachyon 5 amount",
        "type": "number"
    },
    "393": {
        "name": "Tachyon 6",
        "description": "Tachyon 6 amount",
        "type": "number"
    },
    "394": {
        "name": "Total Tachyon Collected",
        "description": "Total Tachyon ever collected",
        "type": "number"
    },
    "395": {
        "name": "Prisma drop from active AC",
        "description": "Prisma drop from active AC",
        "type": "number"
    },
    "396": {
        "name": "Daily Arcane Weapon Drops",
        "description": "Tracks Arcane weapon drop progress",
        "type": "number"
    },
    "397": {
        "name": "Daily Arcane Ring Drops",
        "description": "Tracks Arcane ring drop progress",
        "type": "number"
    },
    "398": {
        "name": "Toggle Tempest Weapon Drops",
        "description": "Tracks Tempest weapon drops",
        "type": "number"
    },
    "399": {
        "name": "Toggle Tempest Ring Drops",
        "description": "Tracks Tempest ring drops",
        "type": "number"
    },
    "400": {
        "name": "Tempest Stone Drops",
        "description": "Tracks Tempest stone drops",
        "type": "number",
        "AI": true
    },
    "401": {
        "name": "Enable AFK Windwalker",
        "description": "Tracks Quest 100 progress",
        "type": "number"
    },
    "402": {
        "name": "Items Discovered in Sneaking",
        "description": "resets daily - controls ability to find pristine charms/symbols",
        "type": "number",
        "AI": true
    },
    "403": {
        "name": "Sailing Progression Unlock",
        "description": "Unlocks sailing-related feature, displays 'S' marker in UI",
        "type": "number",
        "AI": true
    },
    "404": {
        "name": "Asset Positioning Literal 404",
        "description": "Literal numeric value used heavily in asset loading, coordinate layout, and UI element positioning (NOTE: Acts as a literal, not an array index)",
        "type": "number",
        "AI": true
    },
    "405": {
        "name": "UI State Manager 1",
        "description": "State transitions for UI components",
        "type": "number",
        "AI": true
    },
    "406": {
        "name": "UI State Manager 2",
        "description": "State transitions for UI components",
        "type": "number",
        "AI": true
    },
    "407": {
        "name": "UI State Manager 3",
        "description": "State transitions for UI components",
        "type": "number",
        "AI": true
    },
    "408": {
        "name": "Kill Quest Completion",
        "description": "Tracks specific kill quest completion",
        "type": "number",
        "AI": true
    },
    "409": {
        "name": "Quest Item Drop Tracker",
        "description": "Accumulates quest item drops",
        "type": "number",
        "AI": true
    },
    "410": {
        "name": "Daily Spelunky Page reads",
        "description": "Tracks daily Spelunky page reads",
        "type": "number"
    },
    "411": {
        "name": "Gaming Mode Toggle",
        "description": "Controls gaming/Spelunky display mode and affects sprout growth time multiplier",
        "type": "number",
        "AI": true
    },
    "412": {
        "name": "Display Mode Selector",
        "description": "Display mode selector cycling through 3 states",
        "type": "number",
        "AI": true
    },
    "413": {
        "name": "Gaming Palette Selection",
        "description": "Tracks selected gaming palette/tab",
        "type": "number",
        "AI": true
    },
    "414": {
        "name": "Total Jeweled Cog Claims today",
        "description": "Tracks total Jeweled Cog claims today",
        "type": "number"
    },
    "415": {
        "name": "Acorn Shop Purchases",
        "description": "Tracks acorn shop purchase count, affects cost calculations",
        "type": "number",
        "AI": true
    },
    "416": {
        "name": "Exotic Market Purchased for Week",
        "description": "Tracks exotic market purchase count for current week (set to 0 to reset)",
        "type": "number"
    },
    "417": {
        "name": "Quest 107 Progress",
        "description": "Tracks progress for Quest 107 (cap 50)",
        "type": "number",
        "AI": true
    },
    "418": {
        "name": "Hoops Minigame Points",
        "description": "Hoops minigame points",
        "type": "number"
    },
    "419": {
        "name": "Hoops - Damage Bonus",
        "description": "Hoops minigame shop damage bonus",
        "type": "number"
    },
    "420": {
        "name": "Hoops - Coin Drop Bonus",
        "description": "Hoops minigame shop coin drop bonus",
        "type": "number"
    },
    "421": {
        "name": "Hoops - Class EXP Bonus",
        "description": "Hoops minigame shop class EXP bonus",
        "type": "number"
    },
    "422": {
        "name": "Hoops - Skill Efficiency Bonus",
        "description": "Hoops minigame shop skill efficiency bonus",
        "type": "number"
    },
    "423": {
        "name": "Hoops Reset Timer",
        "description": "Time until Hoops minigame resets (negative to play)",
        "type": "number"
    },
    "424": {
        "name": "Hoops Played Today",
        "description": "Number of Hoops minigame played today",
        "type": "number"
    },
    "425": {
        "name": "Divinity God Selection",
        "description": "Tracks selected divinity god (1-10)",
        "type": "number",
        "AI": true
    },
    "426": {
        "name": "Coral Kid - Unlocked",
        "description": "Coral Kid unlocked or not",
        "type": "number"
    },
    "427": {
        "name": "Coral Kid - Divinity XP Bonus",
        "description": "Coral Kid divinity XP bonus level",
        "type": "number"
    },
    "428": {
        "name": "Coral Kid - max blessing level",
        "description": "Coral Kid max blessing level",
        "type": "number"
    },
    "429": {
        "name": "Coral Kid - god rank class xp level",
        "description": "Coral Kid god rank class xp level",
        "type": "number"
    },
    "430": {
        "name": "Coral Kid - divinity minor link bonus level",
        "description": "Coral Kid divinity minor link bonus level",
        "type": "number"
    },
    "431": {
        "name": "Coral Kid - divinity pts coral reef bonus level",
        "description": "Coral Kid divinity pts coral reef bonus level",
        "type": "number"
    },
    "432": {
        "name": "Coral Kid - daily coral reef bonus level",
        "description": "Coral Kid daily coral reef bonus level",
        "type": "number"
    },
    "433": {
        "name": "Coral Kid - NPC Visibility Flag",
        "description": "Controls visibility of Coral actors/NPCs",
        "type": "number"
    },
    "434": {
        "name": "Darts Minigame Points",
        "description": "Darts minigame points",
        "type": "number"
    },
    "435": {
        "name": "Darts Minigame Shop - Extra Damage Bonus",
        "description": "Darts minigame shop extra damage bonus",
        "type": "number"
    },
    "436": {
        "name": "Darts Minigame Shop - Page 1 Talent Points bonus",
        "description": "Darts minigame upgrade level",
        "type": "number"
    },
    "437": {
        "name": "Darts Minigame Shop - Cheaper Vault Upgrades bonus",
        "description": "Darts minigame upgrade level",
        "type": "number"
    },
    "438": {
        "name": "Darts Minigame Shop - Movement Speed bonus",
        "description": "Darts minigame upgrade level",
        "type": "number"
    },
    "439": {
        "name": "Time until Darts Minigame resets, negative number to play",
        "description": "Decrements over time",
        "type": "number"
    },
    "440": {
        "name": "Number of Darts Minigame played today - makes successive reset timer longer",
        "description": "Darts minigame upgrade level",
        "type": "number"
    },
    "441": {
        "name": "Timer System 2",
        "description": "Related to countdown systems",
        "type": "number",
        "AI": true
    },
    "442": {
        "name": "Darts Minigame high score",
        "description": "Darts minigame high score",
        "type": "number"
    },
    "443": {
        "name": "Lavas Dev Streams watched (Tome)",
        "description": "Number of streams watched",
        "type": "number"
    },
    "444": {
        "name": "Sequential Sprite References System",
        "description": "Part of coordinated resource allocation block (447-444) + character animation foundation",
        "type": "number",
        "AI": true
    },
    "445": {
        "name": "Character Leg Animation Frames",
        "description": "Character leg animation frames (lines 148934-148937) + part of 8-element sprite array structure (rl2, ll1, ll2)",
        "type": "number",
        "AI": true
    },
    "446": {
        "name": "Multi-Purpose Resource Identifier",
        "description": "Sound resource ID (lines 238034, 247413) + character limb sprite reference (left hand, line 148931) + portal X-coordinate (line 262888) + mathematical lookup table (blur effects, line 267370)",
        "type": "number",
        "AI": true
    },
    "447": {
        "name": "Sound Resource ID with Audio Looping",
        "description": "Audio system integration with looping functionality + channel-based sound management",
        "type": "number",
        "AI": true
    },
    "448": {
        "name": "Monthly Cycle Tracker",
        "description": "Tracks monthly cycles (division by 2628000ms)",
        "type": "number",
        "AI": true
    },
    "449": {
        "name": "Unused",
        "description": "unused index",
        "type": "number",
        "AI": true
    },
    "450": {
        "name": "Meritocracy Voting Selection Flag",
        "description": "Tracks selected meritocracy voting bonus from predefined bonus array",
        "type": "number",
        "AI": true
    },
    "451": {
        "name": "Meritocracy Voting Weekly Timestamp",
        "description": "Tracks weekly timestamp for meritocracy voting",
        "type": "number",
        "AI": true
    },
    "452": {
        "name": "Quest 107 Counter",
        "description": "Tracks Quest 107 progress",
        "type": "number",
        "AI": true
    },
    "453": {
        "name": "Meritocracy Bonus Selector",
        "description": "Selects active meritocracy voting bonus from predefined bonus array",
        "type": "number",
        "AI": true
    },
    "454": {
        "name": "Clamworks - Current Total",
        "description": "Clamworks current total",
        "type": "number"
    },
    "455": {
        "name": "Clamworks - Pearl Value",
        "description": "Clamworks Pearl Value level",
        "type": "number"
    },
    "456": {
        "name": "Clamworks - Clam Comrades level",
        "description": "Clamworks Clam Comrades level",
        "type": "number"
    },
    "457": {
        "name": "Clamworks - Lucky Day level",
        "description": "Clamworks Lucky Day level",
        "type": "number"
    },
    "458": {
        "name": "Clamworks - Multi-Scalping level",
        "description": "Clamworks Clamworks level",
        "type": "number"
    },
    "459": {
        "name": "Clamworks - Frugality level",
        "description": "Clamworks Clamworks level",
        "type": "number"
    },
    "460": {
        "name": "Clamworks - Pure Pearls level",
        "description": "Controls pearl drop mechanics in specific game areas (w7a6)",
        "type": "number"
    },
    "461": {
        "name": "Clamworks - Encystation Up level",
        "description": "_Leaves_Stored - Resource counter in named index mapping system",
        "type": "number"
    },
    "462": {
        "name": "Clamworks - Shinier Pearls level",
        "description": "Temporary flag that gets reset to zero state",
        "type": "number"
    },
    "463": {
        "name": "Clamworks - Anti Inflation level",
        "description": "_Choppin_Game_Hiscore - High score value, tracks choppin game high score",
        "type": "number"
    },
    "464": {
        "name": "Clamworks - Worker Class level",
        "description": "Experience multiplier component for LUK5 system",
        "type": "number"
    },
    "465": {
        "name": "Clam Progression Counter",
        "description": "Tracks clam upgrade system progression",
        "type": "number",
        "AI": true
    },
    "466": {
        "name": "Killroy Dialogue State",
        "description": "Tracks Killroy dialogue sequence (1-4)",
        "type": "number",
        "AI": true
    },
    "467": {
        "name": "Killroy Gallery Bonus",
        "description": "Killroy gallery bonus",
        "type": "number"
    },
    "468": {
        "name": "Killroy Masterclass Bonus",
        "description": "Killroy masterclass bonus",
        "type": "number"
    },
    "469": {
        "name": "Killroy w7 skill xp bonus",
        "description": "Tracks Killroy shop purchases/rewards",
        "type": "number"
    },
    "470": {
        "name": "Killroy w7 daily coral bonus",
        "description": "Tracks Killroy shop purchases/rewards",
        "type": "number"
    },
    "471": {
        "name": "Killroy 'boost something' bonus",
        "description": "Tracks Killroy shop purchases/rewards",
        "type": "number"
    },
    "472": {
        "name": "Voting Eligibility",
        "description": "Determines meritocracy voting eligibility",
        "type": "number",
        "AI": true
    },
    "473": {
        "name": "Reliquarium Power Divisor",
        "description": "Divisor in Reliquarium power calculations",
        "type": "number",
        "AI": true
    },
    "474": {
        "name": "Current Food Grade",
        "description": "Tracks current food grade level",
        "type": "number",
        "AI": true
    },
    "475": {
        "name": "Quest106/Emporium Unlock",
        "description": "Quest106 completion unlock that enables Emporium dialogue and golden food upgrade tier 3",
        "type": "number",
        "AI": true
    },
    "476": {
        "name": "Friend Bonuses - Active",
        "description": "Active friend bonuses, Format: 'x,yyyy,name;x,yyyy,name' where x=bonus index, yyyy=account level, name=player name",
        "type": "string"
    },
    "477": {
        "name": "Friend Bonuses - Incoming",
        "description": "Incoming friend bonuses, Format: 'x,yyyy,name;x,yyyy,name' where x=bonus index, yyyy=account level, name=player name",
        "type": "string"
    },
    "478": {
        "name": "Spelunking Progress",
        "description": "Tracks progression in spelunking system",
        "type": "number",
        "AI": true
    },
    "479": {
        "name": "Yet Another Printer Multi Days",
        "description": "Days since last sample for legend talent (Brown 4) - cap 20",
        "type": "number"
    },
    "480": {
        "name": "Progression Counter for Upgrades",
        "description": "Progression counter for major upgrades (Grimoire, Compass, Legend Points) with complex calculation formulas",
        "type": "number",
        "AI": true
    },
    "481": {
        "name": "Weekly Time Tracking System",
        "description": "Weekly time tracking system for shop and divinity resets (week number calculations)",
        "type": "number",
        "AI": true
    },
    "482": {
        "name": "Spelunking Tutorial Completion Flag",
        "description": "Tutorial completion flag for Spelunking tutorial system with progress tracking",
        "type": "number",
        "AI": true
    },
    "483": {
        "name": "New Player Bundle System Flag",
        "description": "Bundle system flag for new player rewards and premium content access",
        "type": "number",
        "AI": true
    },
    "484": {
        "name": "Event Counter with Math Formulas",
        "description": "Event counter with mathematical formulas for reward calculations and progression tracking",
        "type": "number",
        "AI": true
    },
    "485": {
        "name": "Event Management Timer System",
        "description": "Timer system for event management and talent calculations with time-sensitive mechanics",
        "type": "number",
        "AI": true
    },
    "486": {
        "name": "Zenith clusters for Zenith market",
        "description": "Zenith market currency system - tracks Zenith currency for purchasing in the Zenith Market",
        "type": "number"
    },
    "487": {
        "name": "Zenith cluster farming toggle",
        "description": "Cluster farming system toggle - 0=OFF, 1=ON. Controls conversion of 1M Statues to Zenith Clusters",
        "type": "number"
    },
    "488": {
        "name": "Cluster Farming Activation Flag",
        "description": "Cluster farming activation system - set to 1 when cluster farming is enabled and active",
        "type": "number"
    },
    "489": {
        "name": "last opened clicker index",
        "description": "last opened clicker index (0-orion owl, 1-poppy kangaroo, 2-bubba seal)",
        "type": "number"
    },
    "490": {
        "name": "Days in a row used Glimmerwick candle",
        "description": "Days in a row used Glimmerwick candle, pity counter",
        "type": "number"
    },
    "491": {
        "name": "Received the reward from the Glimmerwick candle",
        "description": "Received the reward from the Glimmerwick candle, 0=not received, 1=received",
        "type": "number"
    },
    "492": {
        "name": "Daily lock for Glimmerwick candle",
        "description": "Is Glimmerwick usable today, 0=usable, 1=locked",
        "type": "number"
    },
    "493": {
        "name": "Tournament Match Day Lock",
        "description": "Last Played/Claimed Player Match Day lock for Pet Tournaments",
        "type": "number",
        "AI": true
    },
    "494": {
        "name": "Tournament UI Selected Player Index",
        "description": "Currently Selected Player Index for Companion/Tournament UI",
        "type": "number",
        "AI": true
    },
    "495": {
        "name": "Tournament League Badge",
        "description": "Player's Tournament League / Ranked Bracket badge",
        "type": "number",
        "AI": true
    },
    "496": {
        "name": "Tournament Match Fetch Tracker",
        "description": "Last Fetched Tournament Day Tracker",
        "type": "number",
        "AI": true
    },
    "497": {
        "name": "Gaming Minigame High Score",
        "description": "Highest Round Reached High Score in the Log Game Minigame",
        "type": "number"
    },
    "498": {
        "name": "Tournament Lifetime Participation Counter",
        "description": "Lifetime counter for Pet Tournaments Participated In",
        "type": "number"
    },
    "499": {
        "name": "Summoning Grimoire Cost Reduction (%)",
        "description": "Cumulative Grimoire First 3 Mana Colors Upgrade Cost Reduction percentage",
        "type": "number",
        "AI": true
    },
    "500": {
        "name": "Cumulative Spelunking/Sneaking Bonus (%)",
        "description": "Cumulative Spelunking / Sneaking Bonus percentage from Grid Bonus 151",
        "type": "number",
        "AI": true
    },
    "501": {
        "name": "Daily MSA Bonus Claimed Flag",
        "description": "Daily Miniature Soul Apparatus (MSA) Bonus Claimed Boolean flag",
        "type": "number",
        "AI": true
    },
    "502": {
        "name": "Tournament Unread Notification Flag",
        "description": "Unread Tournament Notification UI marker ('NEW' bubble flag)",
        "type": "number",
        "AI": true
    },
    "503": {
        "name": "Unused",
        "description": "No observable behavior in current build",
        "type": "number",
        "AI": true
    },
    "504": {
        "name": "Unused",
        "description": "No observable behavior in current build",
        "type": "number",
        "AI": true
    },
    "505": {
        "name": "Unused",
        "description": "No observable behavior in current build",
        "type": "number",
        "AI": true
    },
    "506": {
        "name": "Unused",
        "description": "No observable behavior in current build",
        "type": "number",
        "AI": true
    },
    "507": {
        "name": "Unused",
        "description": "No observable behavior in current build",
        "type": "number",
        "AI": true
    },
    "508": {
        "name": "Unused",
        "description": "No observable behavior in current build",
        "type": "number",
        "AI": true
    },
    "509": {
        "name": "Unused",
        "description": "No observable behavior in current build",
        "type": "number",
        "AI": true
    },
    "510": {
        "name": "Unused",
        "description": "No observable behavior in current build",
        "type": "number",
        "AI": true
    },
    "511": {
        "name": "Tournament Registration Day Lock",
        "description": "Most recent tournament day used for pet tournament registration gating",
        "type": "number",
        "AI": true
    },
    "512": {
        "name": "Toobus/Goobus 4 Quest Stage",
        "description": "Current completion stage for the multi-step Toobus/Goobus 4 quest chain",
        "type": "number",
        "AI": true
    },
    "513": {
        "name": "Companion Alert Seen Flag",
        "description": "One-time flag marking the companion warning/tooltip animation as seen",
        "type": "number",
        "AI": true
    },
    "514": {
        "name": "Observation Min Roll Streak",
        "description": "Temporary observation progress counter that boosts the Grid MinRoll bonus before reset",
        "type": "number",
        "AI": true
    },
    "515": {
        "name": "Unused",
        "description": "No observable behavior in current build",
        "type": "number",
        "AI": true
    },
    "516": {
        "name": "Pet Mart Gem Reward Day Lock",
        "description": "Last shop day the Pet Mart gem reward was claimed",
        "type": "number",
        "AI": true
    },
    "517": {
        "name": "Workbench Selected Tab",
        "description": "Saved workbench/crafting selection index restored when reopening the UI",
        "type": "number",
        "AI": true
    },
    "518": {
        "name": "Companion 88 Cauldron Bonus Claimed",
        "description": "One-time claim flag for the companion 88 Cauldron bonus reward",
        "type": "number",
        "AI": true
    },
    "519": {
        "name": "Tournament Best Division This Season",
        "description": "Highest pet tournament division reached during the current season",
        "type": "number",
        "AI": true
    },
    "520": {
        "name": "Steam Promo UI State",
        "description": "Finite-state flag for the Play-on-Steam / kill-dialogue promo UI",
        "type": "number",
        "AI": true
    },
    "521": {
        "name": "Vault Upgrade Scroll Position",
        "description": "Saved Vault upgrade screen scroll/offset position",
        "type": "number",
        "AI": true
    },
    "522": {
        "name": "Unused",
        "description": "No observable behavior in current build",
        "type": "number",
        "AI": true
    },
    "523": {
        "name": "Supporter Pack Popup Suppression Flag",
        "description": "High-spender/supporter flag tied to Pack Popup suppression messaging",
        "type": "number",
        "AI": true
    },
    "524": {
        "name": "Guild GP Auto-Contribution Gate",
        "description": "Feature gate controlling automatic Guild GP task contribution flow",
        "type": "number",
        "AI": true
    },
    "525": {
        "name": "Timed Event Popup Suppression Flag",
        "description": "One-time flag gating Happy Hour and related timed event popups",
        "type": "number",
        "AI": true
    },
    "526": {
        "name": "GiveAllEZaccessFR Action Toggle",
        "description": "Feature flag that triggers the GiveAllEZaccessFR action block during Emperor cleanup",
        "type": "number",
        "AI": true
    },
    "527": {
        "name": "Auto-Claim Flag",
        "description": "Feature flag that marks the surrounding reward flow as auto-claimed",
        "type": "number",
        "AI": true
    },
    "528": {
        "name": "Farming Bulk Toggle Mode",
        "description": "Enables the farming UI bulk toggle action for all farm plots",
        "type": "number",
        "AI": true
    },
    "529": {
        "name": "Sailing Autopilot Intensity",
        "description": "Controls queued sailing callbacks and save suppression for automated sailing flows",
        "type": "number",
        "AI": true
    },
    "530": {
        "name": "Cog Trash-All Toggle",
        "description": "Enables the one-click Trash All action in the CogCraft UI",
        "type": "number",
        "AI": true
    },
    "531": {
        "name": "AutoUseAllEggies Action Toggle",
        "description": "Feature flag that triggers the AutoUseAllEggies action block",
        "type": "number",
        "AI": true
    },
    "532": {
        "name": "Unused",
        "description": "No observable behavior in current build",
        "type": "number",
        "AI": true
    },
    "533": {
        "name": "Random Event Bookmark Mode",
        "description": "Enables per-slot marking/highlighting in the random event UI",
        "type": "number",
        "AI": true
    },
    "534": {
        "name": "W5 Gaming Saved Selection",
        "description": "Saved selection/state value restored when launching the W5 gaming event",
        "type": "number",
        "AI": true
    },
    "535": {
        "name": "Ninja Super-Trash Toggle",
        "description": "Enables the automatic Ninja super-trash cleanup routine",
        "type": "number",
        "AI": true
    },
    "536": {
        "name": "Ninja Gem Click Mode",
        "description": "Enables the extra Lucky Ninja Gem click interaction in the Ninja UI",
        "type": "number",
        "AI": true
    },
    "537": {
        "name": "Global Ninja Refresh Toggle",
        "description": "Allows Ninja updates and refreshes to apply across all player slots",
        "type": "number",
        "AI": true
    },
    "538": {
        "name": "Auto Full-Clear Necessary Flag",
        "description": "Toggles whether the AutoFullClearNECESSARY helper reports that an auto full clear is required",
        "type": "number",
        "AI": true
    },
    "601": {
        "name": "Fountain Rubber Duckies",
        "description": "Number of Rubber Duckies found through the Green Water Fountain",
        "type": "number",
        "AI": true
    }
}
